arts_tracking_beams/__init__.py
arts_tracking_beams/__version__.py
arts_tracking_beams/constants.py
arts_tracking_beams/create_synthesised_beam.py
arts_tracking_beams/create_tracking_beam.py
arts_tracking_beams/fits_reader.py
arts_tracking_beams/tools.py
arts_tracking_beams/tracking_beam.py
arts_tracking_beams/static/sbtable-sc4-12tabs-71sbs.txt
test/__init__.py
test/test_create_synthesised_beam.py
test/test_create_tracking_beam.py
test/test_fits_reader.py
test/test_tools.py
test/test_tracking_beam.py
arts_tracking_beams-1.3.dist-info/LICENSE
arts_tracking_beams-1.3.dist-info/METADATA
arts_tracking_beams-1.3.dist-info/WHEEL
arts_tracking_beams-1.3.dist-info/entry_points.txt
arts_tracking_beams-1.3.dist-info/top_level.txt
arts_tracking_beams-1.3.dist-info/RECORD
