Metadata-Version: 2.1
Name: arts-tracking-beams
Version: 1.3
Summary: Create a tracking beam from ARTS tied-array beam data
Home-page: http://github.com/loostrum/arts_tracking_beams
Author: Leon Oostrum
Author-email: oostrum@astron.nl
License: Apache Software License 2.0
Platform: UNKNOWN
Classifier: License :: OSI Approved :: Apache Software License
Classifier: Programming Language :: Python :: 3
Classifier: Operating System :: OS Independent
Requires-Python: >=3.6
Requires-Dist: numpy (>=1.17)
Requires-Dist: astropy
Requires-Dist: tqdm
